zopperuuid/__init__.py
zopperuuid/uuid.py
zopperuuid-0.0.7.dist-info/LICENSE
zopperuuid-0.0.7.dist-info/METADATA
zopperuuid-0.0.7.dist-info/WHEEL
zopperuuid-0.0.7.dist-info/top_level.txt
zopperuuid-0.0.7.dist-info/RECORD
