Metadata-Version: 2.1
Name: zopperuuid
Version: 0.0.7
Summary: This Package will help in generating the UUID
Home-page: https://www.zopper.com
Author: Saurav Sharma
Author-email: saurav.sharma@zopper.com
Classifier: Programming Language :: Python :: 3
Classifier: License :: OSI Approved :: MIT License
Classifier: Operating System :: OS Independent
License-File: LICENSE
